=== Using javap to Inspect Bytecode ===
1. Generated temporary class source file: SimpleMath.java
2. Compiling SimpleMath.java using C:\Program Files\Eclipse Adoptium\jdk-21.0.11.10-hotspot\bin\javac...
   Compilation succeeded.
3. Running javap -c SimpleMath...
--------------------------------------------------------------------------------
   Compiled from "SimpleMath.java"
   public class SimpleMath {
     public SimpleMath();
       Code:
          0: aload_0
          1: invokespecial #1                  // Method java/lang/Object."<init>":()V
          4: return
   
     public int addAndMultiply(int, int);
       Code:
          0: iload_1
          1: iload_2
          2: iadd
          3: istore_3
          4: iload_3
          5: iconst_2
          6: imul
          7: ireturn
   }
--------------------------------------------------------------------------------

=== Interpretation of the Bytecode ===
- iload_1 & iload_2: Load the int parameters 'a' and 'b' onto the operand stack.
- iadd: Pops two integers from the stack, adds them, and pushes the result back.
- istore_3: Pops the sum result and stores it in local variable 3 ('sum').
- iload_3: Loads the local variable 3 ('sum') onto the stack.
- iconst_2: Pushes the integer constant '2' onto the stack.
- imul: Pops two values (sum and 2) from the stack, multiplies them, and pushes the result.
- ireturn: Returns the integer result from the method.

4. Cleaned up temporary files.
